dolphinflow/__init__.py
dolphinflow/dolphinflow.py
dolphinflow/dolphinflow_8bit.py
dolphinflow-0.2.0.dist-info/licenses/LICENSE
dolphinflow-0.2.0.dist-info/METADATA
dolphinflow-0.2.0.dist-info/WHEEL
dolphinflow-0.2.0.dist-info/top_level.txt
dolphinflow-0.2.0.dist-info/RECORD
