Metadata-Version: 2.4
Name: dolphinflow
Version: 0.2.0
Summary: DolphinFlow: A robust, low-maintenance optimizer for PyTorch.
Author-email: Eric Hartford <ehartford@gmail.com>
License:                                  Apache License
Project-URL: Homepage, https://github.com/cognitivecomputations/dolphinflow-optimizer
Project-URL: Bug Tracker, https://github.com/cognitivecomputations/dolphinflow-optimizer/issues
Keywords: pytorch,optimizer,machine learning,deep learning
Classifier: Development Status :: 4 - Beta
Classifier: Intended Audience :: Developers
Classifier: Intended Audience :: Science/Research
Classifier: License :: OSI Approved :: MIT License
Classifier: Operating System :: OS Independent
Classifier: Programming Language :: Python :: 3
Classifier: Programming Language :: Python :: 3.8
Classifier: Programming Language :: Python :: 3.9
Classifier: Programming Language :: Python :: 3.10
Classifier: Programming Language :: Python :: 3.11
Requires-Python: >=3.8
License-File: LICENSE
Requires-Dist: torch>=1.10
Provides-Extra: bnb
Requires-Dist: bitsandbytes>=0.41.0; extra == "bnb"
Dynamic: license-file
